LICENSE
nonebot_plugin_help/__init__.py
nonebot_plugin_help/config.py
nonebot_plugin_help/handler.py
nonebot_plugin_help-0.6.0.dist-info/LICENSE
nonebot_plugin_help-0.6.0.dist-info/METADATA
nonebot_plugin_help-0.6.0.dist-info/WHEEL
nonebot_plugin_help-0.6.0.dist-info/RECORD
