Metadata-Version: 2.1
Name: nonebot-plugin-help
Version: 0.6.0
Summary: A general help lister for nonebot2 plugins
Home-page: https://github.com/XZhouQD/nonebot-plugin-help
License: AGPL v3
Author: XZhouQD
Author-email: X.Zhou.QD@hotmail.com
Requires-Python: >=3.8.0,<4.0.0
Classifier: License :: Other/Proprietary License
Classifier: Programming Language :: Python :: 3
Classifier: Programming Language :: Python :: 3.8
Classifier: Programming Language :: Python :: 3.9
Classifier: Programming Language :: Python :: 3.10
Classifier: Programming Language :: Python :: 3.11
Requires-Dist: nonebot2 (>=2.0.0,<3.0.0)
Project-URL: Repository, https://github.com/XZhouQD/nonebot-plugin-help
